plotbiox/__init__.py
plotbiox/config.py
plotbiox/versions.py
plotbiox/data/.DS_Store
plotbiox/data/example_data/pvalue.txt
plotbiox/data/natural_earth/ne_10m_admin_0_countries/.DS_Store
plotbiox/data/natural_earth/ne_10m_admin_0_countries/ne_10m_admin_0_countries.README.html
plotbiox/data/natural_earth/ne_10m_admin_0_countries/ne_10m_admin_0_countries.VERSION.txt
plotbiox/data/natural_earth/ne_10m_admin_0_countries/ne_10m_admin_0_countries.changes_log.csv
plotbiox/data/natural_earth/ne_10m_admin_0_countries/ne_10m_admin_0_countries.changes_log.csv.md
plotbiox/data/natural_earth/ne_10m_admin_0_countries/ne_10m_admin_0_countries.cpg
plotbiox/data/natural_earth/ne_10m_admin_0_countries/ne_10m_admin_0_countries.dbf
plotbiox/data/natural_earth/ne_10m_admin_0_countries/ne_10m_admin_0_countries.new_names.csv
plotbiox/data/natural_earth/ne_10m_admin_0_countries/ne_10m_admin_0_countries.prj
plotbiox/data/natural_earth/ne_10m_admin_0_countries/ne_10m_admin_0_countries.shp
plotbiox/data/natural_earth/ne_10m_admin_0_countries/ne_10m_admin_0_countries.shp.changes_log.csv
plotbiox/data/natural_earth/ne_10m_admin_0_countries/ne_10m_admin_0_countries.shp.changes_log.csv.md
plotbiox/data/natural_earth/ne_10m_admin_0_countries/ne_10m_admin_0_countries.shp.new_names.csv
plotbiox/data/natural_earth/ne_10m_admin_0_countries/ne_10m_admin_0_countries.shp.summary_log.csv
plotbiox/data/natural_earth/ne_10m_admin_0_countries/ne_10m_admin_0_countries.shp.summary_log.csv.md
plotbiox/data/natural_earth/ne_10m_admin_0_countries/ne_10m_admin_0_countries.shx
plotbiox/data/natural_earth/ne_10m_admin_0_countries/ne_10m_admin_0_countries.summary_log.csv
plotbiox/data/natural_earth/ne_10m_admin_0_countries/ne_10m_admin_0_countries.summary_log.csv.md
plotbiox/map/__init__.py
plotbiox/map/map_plot.py
plotbiox/quantitative_genomics/__init__.py
plotbiox/quantitative_genomics/gwas_plot.py
PlotBiox-0.0.2.dist-info/LICENSE
PlotBiox-0.0.2.dist-info/METADATA
PlotBiox-0.0.2.dist-info/WHEEL
PlotBiox-0.0.2.dist-info/top_level.txt
PlotBiox-0.0.2.dist-info/RECORD
